{
  "Name": "Flag Unit",
  "Colour": "#30F5E5",
  "InputPins": [
    {
      "Name": "In A1",
      "ID": 540288293,
      "PositionY": 4.66666651,
      "ColourThemeName": "Red"
    },
    {
      "Name": "In A2",
      "ID": 2039172251,
      "PositionY": 4.311111,
      "ColourThemeName": "Red"
    },
    {
      "Name": "In A3",
      "ID": 636433124,
      "PositionY": 3.96666646,
      "ColourThemeName": "Red"
    },
    {
      "Name": "In A4",
      "ID": 755347116,
      "PositionY": 3.63333344,
      "ColourThemeName": "Red"
    },
    {
      "Name": "In A5",
      "ID": 1950206145,
      "PositionY": 3.29999971,
      "ColourThemeName": "Red"
    },
    {
      "Name": "In A6",
      "ID": 331410683,
      "PositionY": 2.95555544,
      "ColourThemeName": "Red"
    },
    {
      "Name": "In A7",
      "ID": 409318201,
      "PositionY": 2.6,
      "ColourThemeName": "Red"
    },
    {
      "Name": "In A8",
      "ID": 1149081360,
      "PositionY": 2.24444437,
      "ColourThemeName": "Red"
    },
    {
      "Name": "Carry",
      "ID": 1701255904,
      "PositionY": -4.04444456,
      "ColourThemeName": "Red"
    }
  ],
  "OutputPins": [
    {
      "Name": "Zero",
      "ID": 1248554483,
      "PositionY": 4.5333333,
      "ColourThemeName": "Red"
    },
    {
      "Name": "Carry",
      "ID": 2027253934,
      "PositionY": 3.98888874,
      "ColourThemeName": "Red"
    }
  ],
  "SubChips": [
    {
      "Name": "NOT",
      "ID": 1861226475,
      "Points": [
        {
          "X": -4.477778,
          "Y": 4.58694458
        }
      ],
      "Data": null
    },
    {
      "Name": "NOT",
      "ID": 906341546,
      "Points": [
        {
          "X": -4.477778,
          "Y": 4.03194427
        }
      ],
      "Data": null
    },
    {
      "Name": "NOT",
      "ID": 1326398738,
      "Points": [
        {
          "X": -4.477778,
          "Y": 3.47694445
        }
      ],
      "Data": null
    },
    {
      "Name": "NOT",
      "ID": 1923894631,
      "Points": [
        {
          "X": -4.477778,
          "Y": 2.92194462
        }
      ],
      "Data": null
    },
    {
      "Name": "NOT",
      "ID": 1823068063,
      "Points": [
        {
          "X": -4.477778,
          "Y": 2.36694479
        }
      ],
      "Data": null
    },
    {
      "Name": "NOT",
      "ID": 375643017,
      "Points": [
        {
          "X": -4.477778,
          "Y": 1.81194484
        }
      ],
      "Data": null
    },
    {
      "Name": "NOT",
      "ID": 1874790809,
      "Points": [
        {
          "X": -4.477778,
          "Y": 1.25694489
        }
      ],
      "Data": null
    },
    {
      "Name": "NOT",
      "ID": 408260584,
      "Points": [
        {
          "X": -4.477778,
          "Y": 0.701944947
        }
      ],
      "Data": null
    },
    {
      "Name": "AND",
      "ID": 504524486,
      "Points": [
        {
          "X": -3.1555562,
          "Y": 4.35555553
        }
      ],
      "Data": null
    },
    {
      "Name": "AND",
      "ID": 1138490199,
      "Points": [
        {
          "X": -3.08888912,
          "Y": 3.8111105
        }
      ],
      "Data": null
    },
    {
      "Name": "AND",
      "ID": 1320977130,
      "Points": [
        {
          "X": -2.95555544,
          "Y": 3.27777743
        }
      ],
      "Data": null
    },
    {
      "Name": "AND",
      "ID": 480400661,
      "Points": [
        {
          "X": -2.84444547,
          "Y": 2.72222233
        }
      ],
      "Data": null
    },
    {
      "Name": "AND",
      "ID": 2138057182,
      "Points": [
        {
          "X": -2.6888895,
          "Y": 2.17777729
        }
      ],
      "Data": null
    },
    {
      "Name": "AND",
      "ID": 272883280,
      "Points": [
        {
          "X": -2.55555463,
          "Y": 1.62222147
        }
      ],
      "Data": null
    },
    {
      "Name": "AND",
      "ID": 690342803,
      "Points": [
        {
          "X": -2.45555663,
          "Y": 1.06666744
        }
      ],
      "Data": null
    }
  ],
  "Connections": [
    {
      "Source": {
        "PinType": 4,
        "SubChipID": 1861226475,
        "PinID": 1
      },
      "Target": {
        "PinType": 3,
        "SubChipID": 504524486,
        "PinID": 0
      },
      "WirePoints": [
        {
          "X": -3.927778,
          "Y": 4.58694458
        },
        {
          "X": -3.70555663,
          "Y": 4.47555542
        }
      ],
      "ColourThemeName": "Red"
    },
    {
      "Source": {
        "PinType": 4,
        "SubChipID": 906341546,
        "PinID": 1
      },
      "Target": {
        "PinType": 3,
        "SubChipID": 504524486,
        "PinID": 1
      },
      "WirePoints": [
        {
          "X": -3.927778,
          "Y": 4.03194427
        },
        {
          "X": -3.70555663,
          "Y": 4.23555565
        }
      ],
      "ColourThemeName": "Red"
    },
    {
      "Source": {
        "PinType": 4,
        "SubChipID": 504524486,
        "PinID": 2
      },
      "Target": {
        "PinType": 3,
        "SubChipID": 1138490199,
        "PinID": 0
      },
      "WirePoints": [
        {
          "X": -2.60555625,
          "Y": 4.35555553
        },
        {
          "X": -3.63888931,
          "Y": 3.93111038
        }
      ],
      "ColourThemeName": "Red"
    },
    {
      "Source": {
        "PinType": 4,
        "SubChipID": 1326398738,
        "PinID": 1
      },
      "Target": {
        "PinType": 3,
        "SubChipID": 1138490199,
        "PinID": 1
      },
      "WirePoints": [
        {
          "X": -3.927778,
          "Y": 3.47694445
        },
        {
          "X": -3.63888955,
          "Y": 3.69111061
        }
      ],
      "ColourThemeName": "Red"
    },
    {
      "Source": {
        "PinType": 4,
        "SubChipID": 1138490199,
        "PinID": 2
      },
      "Target": {
        "PinType": 3,
        "SubChipID": 1320977130,
        "PinID": 0
      },
      "WirePoints": [
        {
          "X": -2.53888917,
          "Y": 3.8111105
        },
        {
          "X": -3.50555563,
          "Y": 3.39777732
        }
      ],
      "ColourThemeName": "Red"
    },
    {
      "Source": {
        "PinType": 4,
        "SubChipID": 1923894631,
        "PinID": 1
      },
      "Target": {
        "PinType": 3,
        "SubChipID": 1320977130,
        "PinID": 1
      },
      "WirePoints": [
        {
          "X": -3.927778,
          "Y": 2.92194462
        },
        {
          "X": -3.50555587,
          "Y": 3.15777755
        }
      ],
      "ColourThemeName": "Red"
    },
    {
      "Source": {
        "PinType": 4,
        "SubChipID": 1823068063,
        "PinID": 1
      },
      "Target": {
        "PinType": 3,
        "SubChipID": 480400661,
        "PinID": 1
      },
      "WirePoints": [
        {
          "X": -3.927778,
          "Y": 2.36694479
        },
        {
          "X": -3.39444566,
          "Y": 2.60222244
        }
      ],
      "ColourThemeName": "Red"
    },
    {
      "Source": {
        "PinType": 4,
        "SubChipID": 1320977130,
        "PinID": 2
      },
      "Target": {
        "PinType": 3,
        "SubChipID": 480400661,
        "PinID": 0
      },
      "WirePoints": [
        {
          "X": -2.40555549,
          "Y": 3.27777743
        },
        {
          "X": -3.39444542,
          "Y": 2.84222221
        }
      ],
      "ColourThemeName": "Red"
    },
    {
      "Source": {
        "PinType": 4,
        "SubChipID": 480400661,
        "PinID": 2
      },
      "Target": {
        "PinType": 3,
        "SubChipID": 2138057182,
        "PinID": 0
      },
      "WirePoints": [
        {
          "X": -2.29444551,
          "Y": 2.72222233
        },
        {
          "X": -3.23888969,
          "Y": 2.29777718
        }
      ],
      "ColourThemeName": "Red"
    },
    {
      "Source": {
        "PinType": 4,
        "SubChipID": 375643017,
        "PinID": 1
      },
      "Target": {
        "PinType": 3,
        "SubChipID": 2138057182,
        "PinID": 1
      },
      "WirePoints": [
        {
          "X": -3.927778,
          "Y": 1.81194484
        },
        {
          "X": -3.23889,
          "Y": 2.0577774
        }
      ],
      "ColourThemeName": "Red"
    },
    {
      "Source": {
        "PinType": 4,
        "SubChipID": 2138057182,
        "PinID": 2
      },
      "Target": {
        "PinType": 3,
        "SubChipID": 272883280,
        "PinID": 0
      },
      "WirePoints": [
        {
          "X": -2.13888955,
          "Y": 2.17777729
        },
        {
          "X": -3.10555458,
          "Y": 1.74222147
        }
      ],
      "ColourThemeName": "Red"
    },
    {
      "Source": {
        "PinType": 4,
        "SubChipID": 1874790809,
        "PinID": 1
      },
      "Target": {
        "PinType": 3,
        "SubChipID": 272883280,
        "PinID": 1
      },
      "WirePoints": [
        {
          "X": -3.927778,
          "Y": 1.25694489
        },
        {
          "X": -3.10555482,
          "Y": 1.50222147
        }
      ],
      "ColourThemeName": "Red"
    },
    {
      "Source": {
        "PinType": 4,
        "SubChipID": 272883280,
        "PinID": 2
      },
      "Target": {
        "PinType": 3,
        "SubChipID": 690342803,
        "PinID": 0
      },
      "WirePoints": [
        {
          "X": -2.00555468,
          "Y": 1.62222147
        },
        {
          "X": -3.00555658,
          "Y": 1.18666744
        }
      ],
      "ColourThemeName": "Red"
    },
    {
      "Source": {
        "PinType": 4,
        "SubChipID": 408260584,
        "PinID": 1
      },
      "Target": {
        "PinType": 3,
        "SubChipID": 690342803,
        "PinID": 1
      },
      "WirePoints": [
        {
          "X": -3.927778,
          "Y": 0.701944947
        },
        {
          "X": -3.00555682,
          "Y": 0.946667433
        }
      ],
      "ColourThemeName": "Red"
    },
    {
      "Source": {
        "PinType": 4,
        "SubChipID": 690342803,
        "PinID": 2
      },
      "Target": {
        "PinType": 2,
        "SubChipID": 0,
        "PinID": 1248554483
      },
      "WirePoints": [
        {
          "X": -1.90555668,
          "Y": 1.06666744
        },
        {
          "X": 7.837778,
          "Y": 4.5333333
        }
      ],
      "ColourThemeName": "Red"
    },
    {
      "Source": {
        "PinType": 1,
        "SubChipID": 0,
        "PinID": 540288293
      },
      "Target": {
        "PinType": 3,
        "SubChipID": 1861226475,
        "PinID": 0
      },
      "WirePoints": [
        {
          "X": -7.837778,
          "Y": 4.66666651
        },
        {
          "X": -5.027778,
          "Y": 4.58694458
        }
      ],
      "ColourThemeName": "Red"
    },
    {
      "Source": {
        "PinType": 1,
        "SubChipID": 0,
        "PinID": 2039172251
      },
      "Target": {
        "PinType": 3,
        "SubChipID": 906341546,
        "PinID": 0
      },
      "WirePoints": [
        {
          "X": -7.837778,
          "Y": 4.311111
        },
        {
          "X": -5.027778,
          "Y": 4.03194427
        }
      ],
      "ColourThemeName": "Red"
    },
    {
      "Source": {
        "PinType": 1,
        "SubChipID": 0,
        "PinID": 636433124
      },
      "Target": {
        "PinType": 3,
        "SubChipID": 1326398738,
        "PinID": 0
      },
      "WirePoints": [
        {
          "X": -7.837778,
          "Y": 3.96666646
        },
        {
          "X": -5.027778,
          "Y": 3.47694445
        }
      ],
      "ColourThemeName": "Red"
    },
    {
      "Source": {
        "PinType": 1,
        "SubChipID": 0,
        "PinID": 755347116
      },
      "Target": {
        "PinType": 3,
        "SubChipID": 1923894631,
        "PinID": 0
      },
      "WirePoints": [
        {
          "X": -7.837778,
          "Y": 3.63333344
        },
        {
          "X": -5.027778,
          "Y": 2.92194462
        }
      ],
      "ColourThemeName": "Red"
    },
    {
      "Source": {
        "PinType": 1,
        "SubChipID": 0,
        "PinID": 1950206145
      },
      "Target": {
        "PinType": 3,
        "SubChipID": 1823068063,
        "PinID": 0
      },
      "WirePoints": [
        {
          "X": -7.837778,
          "Y": 3.29999971
        },
        {
          "X": -5.027778,
          "Y": 2.36694479
        }
      ],
      "ColourThemeName": "Red"
    },
    {
      "Source": {
        "PinType": 1,
        "SubChipID": 0,
        "PinID": 331410683
      },
      "Target": {
        "PinType": 3,
        "SubChipID": 375643017,
        "PinID": 0
      },
      "WirePoints": [
        {
          "X": -7.837778,
          "Y": 2.95555544
        },
        {
          "X": -5.027778,
          "Y": 1.81194484
        }
      ],
      "ColourThemeName": "Red"
    },
    {
      "Source": {
        "PinType": 1,
        "SubChipID": 0,
        "PinID": 409318201
      },
      "Target": {
        "PinType": 3,
        "SubChipID": 1874790809,
        "PinID": 0
      },
      "WirePoints": [
        {
          "X": -7.837778,
          "Y": 2.6
        },
        {
          "X": -5.027778,
          "Y": 1.25694489
        }
      ],
      "ColourThemeName": "Red"
    },
    {
      "Source": {
        "PinType": 1,
        "SubChipID": 0,
        "PinID": 1149081360
      },
      "Target": {
        "PinType": 3,
        "SubChipID": 408260584,
        "PinID": 0
      },
      "WirePoints": [
        {
          "X": -7.837778,
          "Y": 2.24444437
        },
        {
          "X": -7.72222233,
          "Y": 2.17777777
        },
        {
          "X": -5.027778,
          "Y": 0.701944947
        }
      ],
      "ColourThemeName": "Red"
    },
    {
      "Source": {
        "PinType": 1,
        "SubChipID": 0,
        "PinID": 1701255904
      },
      "Target": {
        "PinType": 2,
        "SubChipID": 0,
        "PinID": 2027253934
      },
      "WirePoints": [
        {
          "X": -7.837778,
          "Y": -4.04444456
        },
        {
          "X": 7.837778,
          "Y": 3.98888874
        }
      ],
      "ColourThemeName": "Red"
    }
  ]
}